README.rst
setup.cfg
setup.py
peek_worker/CeleryApp.py
peek_worker/PeekWorkerConfig.py
peek_worker/PeekWorkerConfigTest.py
peek_worker/TempUnitTest.py
peek_worker/__init__.py
peek_worker/run_peek_worker.py
peek_worker/winsvc_peek_worker.py
peek_worker.egg-info/PKG-INFO
peek_worker.egg-info/SOURCES.txt
peek_worker.egg-info/dependency_links.txt
peek_worker.egg-info/entry_points.txt
peek_worker.egg-info/not-zip-safe
peek_worker.egg-info/requires.txt
peek_worker.egg-info/top_level.txt
peek_worker/plugin/PeekWorkerPlatformHook.py
peek_worker/plugin/WorkerPluginLoader.py
peek_worker/plugin/WorkerPluginLoaderTest.py
peek_worker/plugin/__init__.py
peek_worker/sw_install/PeekSwInstallManager.py
peek_worker/sw_install/PluginSwInstallManager.py
peek_worker/sw_install/__init__.py