Metadata-Version: 1.1
Name: peek-worker
Version: 1.3.1
Summary: Peek Platform - Worker Service
Home-page: https://github.com/Synerty/peek-worker
Author: Synerty
Author-email: contact@synerty.com
License: UNKNOWN
Download-URL: https://github.com/Synerty/peek-worker/tarball/1.3.1
Keywords: Peek,Python,Platform,synerty
Platform: UNKNOWN
Classifier: Programming Language :: Python :: 3.5
